[
{ "seq_id" : 96, "qsl_idx" : 4165, "data" : "00006544" },
{ "seq_id" : 97, "qsl_idx" : 45964, "data" : "00400644" },
{ "seq_id" : 98, "qsl_idx" : 1778, "data" : "00001843" },
{ "seq_id" : 99, "qsl_idx" : 9792, "data" : "00C02844" },
{ "seq_id" : 100, "qsl_idx" : 11401, "data" : "00000E43" },
{ "seq_id" : 101, "qsl_idx" : 36094, "data" : "0000A843" },
{ "seq_id" : 102, "qsl_idx" : 24754, "data" : "00809B43" },
{ "seq_id" : 103, "qsl_idx" : 1756, "data" : "00C00344" },
{ "seq_id" : 104, "qsl_idx" : 42885, "data" : "0000EC42" },
{ "seq_id" : 105, "qsl_idx" : 14030, "data" : "00009F43" },
{ "seq_id" : 106, "qsl_idx" : 20798, "data" : "00004C44" },
{ "seq_id" : 107, "qsl_idx" : 47974, "data" : "00406844" },
{ "seq_id" : 108, "qsl_idx" : 9919, "data" : "00C04944" },
{ "seq_id" : 109, "qsl_idx" : 25852, "data" : "00C07444" },
{ "seq_id" : 110, "qsl_idx" : 21550, "data" : "00005F44" },
{ "seq_id" : 111, "qsl_idx" : 38792, "data" : "00001043" },
{ "seq_id" : 112, "qsl_idx" : 31170, "data" : "00004041" },
{ "seq_id" : 113, "qsl_idx" : 206, "data" : "00001243" },
{ "seq_id" : 114, "qsl_idx" : 27914, "data" : "00406C44" },
{ "seq_id" : 115, "qsl_idx" : 41343, "data" : "0080C343" },
{ "seq_id" : 116, "qsl_idx" : 11691, "data" : "0080FE43" },
{ "seq_id" : 117, "qsl_idx" : 31828, "data" : "00000442" },
{ "seq_id" : 118, "qsl_idx" : 9373, "data" : "00009841" },
{ "seq_id" : 119, "qsl_idx" : 34177, "data" : "00008040" },
{ "seq_id" : 120, "qsl_idx" : 27730, "data" : "00000B43" },
{ "seq_id" : 121, "qsl_idx" : 28297, "data" : "00801244" },
{ "seq_id" : 122, "qsl_idx" : 9957, "data" : "0080D443" },
{ "seq_id" : 123, "qsl_idx" : 1754, "data" : "0000F343" },
{ "seq_id" : 124, "qsl_idx" : 33679, "data" : "00006E44" },
{ "seq_id" : 125, "qsl_idx" : 16977, "data" : "00804444" },
{ "seq_id" : 126, "qsl_idx" : 31870, "data" : "00C06044" },
{ "seq_id" : 127, "qsl_idx" : 13544, "data" : "00804444" },
{ "seq_id" : 32, "qsl_idx" : 24106, "data" : "0080B943" },
{ "seq_id" : 33, "qsl_idx" : 42809, "data" : "00005743" },
{ "seq_id" : 34, "qsl_idx" : 10600, "data" : "0000AD43" },
{ "seq_id" : 35, "qsl_idx" : 23433, "data" : "00009C42" },
{ "seq_id" : 36, "qsl_idx" : 44194, "data" : "00809143" },
{ "seq_id" : 37, "qsl_idx" : 9959, "data" : "00402B44" },
{ "seq_id" : 38, "qsl_idx" : 11585, "data" : "00002643" },
{ "seq_id" : 39, "qsl_idx" : 10929, "data" : "00C03544" },
{ "seq_id" : 40, "qsl_idx" : 26967, "data" : "00805344" },
{ "seq_id" : 41, "qsl_idx" : 49119, "data" : "0000B043" },
{ "seq_id" : 42, "qsl_idx" : 25142, "data" : "00406844" },
{ "seq_id" : 43, "qsl_idx" : 11820, "data" : "0000DE43" },
{ "seq_id" : 44, "qsl_idx" : 41890, "data" : "0080D843" },
{ "seq_id" : 45, "qsl_idx" : 40536, "data" : "00003444" },
{ "seq_id" : 46, "qsl_idx" : 36603, "data" : "00003544" },
{ "seq_id" : 47, "qsl_idx" : 10786, "data" : "00004644" },
{ "seq_id" : 48, "qsl_idx" : 44314, "data" : "00000944" },
{ "seq_id" : 49, "qsl_idx" : 10082, "data" : "00C03C44" },
{ "seq_id" : 50, "qsl_idx" : 4090, "data" : "00809D43" },
{ "seq_id" : 51, "qsl_idx" : 5525, "data" : "0080DF43" },
{ "seq_id" : 52, "qsl_idx" : 38601, "data" : "00006B44" },
{ "seq_id" : 53, "qsl_idx" : 21822, "data" : "0000DC42" },
{ "seq_id" : 54, "qsl_idx" : 15784, "data" : "00009043" },
{ "seq_id" : 55, "qsl_idx" : 47674, "data" : "00003442" },
{ "seq_id" : 56, "qsl_idx" : 15558, "data" : "00C00B44" },
{ "seq_id" : 57, "qsl_idx" : 25697, "data" : "0000B943" },
{ "seq_id" : 58, "qsl_idx" : 36388, "data" : "00007B43" },
{ "seq_id" : 59, "qsl_idx" : 15537, "data" : "00C02644" },
{ "seq_id" : 60, "qsl_idx" : 25211, "data" : "00809943" },
{ "seq_id" : 61, "qsl_idx" : 31937, "data" : "0000A642" },
{ "seq_id" : 62, "qsl_idx" : 43959, "data" : "00400644" },
{ "seq_id" : 63, "qsl_idx" : 46633, "data" : "00004244" },
{ "seq_id" : 128, "qsl_idx" : 13646, "data" : "00007844" },
{ "seq_id" : 129, "qsl_idx" : 2304, "data" : "00809643" },
{ "seq_id" : 130, "qsl_idx" : 24050, "data" : "00008243" },
{ "seq_id" : 131, "qsl_idx" : 29393, "data" : "0080BD43" },
{ "seq_id" : 132, "qsl_idx" : 4192, "data" : "00000144" },
{ "se

...

ta" : "0080CC43" },
{ "seq_id" : 49534, "qsl_idx" : 40243, "data" : "00000443" },
{ "seq_id" : 49535, "qsl_idx" : 48417, "data" : "00C05844" },
{ "seq_id" : 49824, "qsl_idx" : 23578, "data" : "00405944" },
{ "seq_id" : 49825, "qsl_idx" : 10544, "data" : "00005C42" },
{ "seq_id" : 49826, "qsl_idx" : 18627, "data" : "00803444" },
{ "seq_id" : 49827, "qsl_idx" : 36221, "data" : "00804444" },
{ "seq_id" : 49828, "qsl_idx" : 30882, "data" : "00001443" },
{ "seq_id" : 49829, "qsl_idx" : 44177, "data" : "00001744" },
{ "seq_id" : 49830, "qsl_idx" : 35469, "data" : "00005F44" },
{ "seq_id" : 49831, "qsl_idx" : 32733, "data" : "00001144" },
{ "seq_id" : 49832, "qsl_idx" : 11410, "data" : "00005D44" },
{ "seq_id" : 49833, "qsl_idx" : 11643, "data" : "00002144" },
{ "seq_id" : 49834, "qsl_idx" : 7365, "data" : "00004A43" },
{ "seq_id" : 49835, "qsl_idx" : 42807, "data" : "00804444" },
{ "seq_id" : 49836, "qsl_idx" : 17869, "data" : "00003744" },
{ "seq_id" : 49837, "qsl_idx" : 8368, "data" : "00C00244" },
{ "seq_id" : 49838, "qsl_idx" : 31592, "data" : "00407844" },
{ "seq_id" : 49839, "qsl_idx" : 6859, "data" : "0000E442" },
{ "seq_id" : 49840, "qsl_idx" : 938, "data" : "00000243" },
{ "seq_id" : 49841, "qsl_idx" : 33442, "data" : "0080E243" },
{ "seq_id" : 49842, "qsl_idx" : 7962, "data" : "00005043" },
{ "seq_id" : 49843, "qsl_idx" : 18802, "data" : "00400544" },
{ "seq_id" : 49844, "qsl_idx" : 44222, "data" : "0080A043" },
{ "seq_id" : 49845, "qsl_idx" : 20689, "data" : "0000A642" },
{ "seq_id" : 49846, "qsl_idx" : 48756, "data" : "0000AE43" },
{ "seq_id" : 49847, "qsl_idx" : 40461, "data" : "00404744" },
{ "seq_id" : 49848, "qsl_idx" : 30173, "data" : "00802744" },
{ "seq_id" : 49849, "qsl_idx" : 14198, "data" : "00C04844" },
{ "seq_id" : 49850, "qsl_idx" : 27467, "data" : "00406344" },
{ "seq_id" : 49851, "qsl_idx" : 14400, "data" : "00804244" },
{ "seq_id" : 49852, "qsl_idx" : 45986, "data" : "00004A43" },
{ "seq_id" : 49853, "qsl_idx" : 42081, "data" : "00005442" },
{ "seq_id" : 49854, "qsl_idx" : 28106, "data" : "00000041" },
{ "seq_id" : 49855, "qsl_idx" : 15007, "data" : "0080D443" },
{ "seq_id" : 49792, "qsl_idx" : 29422, "data" : "00C01E44" },
{ "seq_id" : 49793, "qsl_idx" : 41524, "data" : "00C04C44" },
{ "seq_id" : 49794, "qsl_idx" : 28851, "data" : "0000E442" },
{ "seq_id" : 49795, "qsl_idx" : 30636, "data" : "00005043" },
{ "seq_id" : 49796, "qsl_idx" : 12902, "data" : "00805D44" },
{ "seq_id" : 49797, "qsl_idx" : 35609, "data" : "00001E44" },
{ "seq_id" : 49798, "qsl_idx" : 1605, "data" : "00405844" },
{ "seq_id" : 49799, "qsl_idx" : 18847, "data" : "00001C42" },
{ "seq_id" : 49800, "qsl_idx" : 10458, "data" : "00806044" },
{ "seq_id" : 49801, "qsl_idx" : 1849, "data" : "0000CA42" },
{ "seq_id" : 49802, "qsl_idx" : 36442, "data" : "00004243" },
{ "seq_id" : 49803, "qsl_idx" : 7866, "data" : "00C03344" },
{ "seq_id" : 49804, "qsl_idx" : 8066, "data" : "00C01744" },
{ "seq_id" : 49805, "qsl_idx" : 5522, "data" : "0000E243" },
{ "seq_id" : 49806, "qsl_idx" : 36921, "data" : "00004244" },
{ "seq_id" : 49807, "qsl_idx" : 15501, "data" : "0080BF43" },
{ "seq_id" : 49808, "qsl_idx" : 42219, "data" : "00006443" },
{ "seq_id" : 49809, "qsl_idx" : 39060, "data" : "00401E44" },
{ "seq_id" : 49810, "qsl_idx" : 6867, "data" : "00003A44" },
{ "seq_id" : 49811, "qsl_idx" : 37940, "data" : "00001041" },
{ "seq_id" : 49812, "qsl_idx" : 782, "data" : "00001E44" },
{ "seq_id" : 49813, "qsl_idx" : 41293, "data" : "0080BD43" },
{ "seq_id" : 49814, "qsl_idx" : 11617, "data" : "00C01C44" },
{ "seq_id" : 49815, "qsl_idx" : 2275, "data" : "00C04844" },
{ "seq_id" : 49816, "qsl_idx" : 44846, "data" : "0000FC43" },
{ "seq_id" : 49817, "qsl_idx" : 30162, "data" : "00001042" },
{ "seq_id" : 49818, "qsl_idx" : 48860, "data" : "00001443" },
{ "seq_id" : 49819, "qsl_idx" : 3122, "data" : "00C03E44" },
{ "seq_id" : 49820, "qsl_idx" : 19477, "data" : "0000DA43" },
{ "seq_id" : 49821, "qsl_idx" : 6042, "data" : "0080F543" },
{ "seq_id" : 49822, "qsl_idx" : 15633, "data" : "00007144" },
{ "seq_id" : 49823, "qsl_idx" : 31537, "data" : "00006844" }
]
